elephant-1.1.1.dist-info/LICENSE.txt
elephant-1.1.1.dist-info/top_level.txt
elephant-1.1.1.dist-info/RECORD
elephant-1.1.1.dist-info/METADATA
elephant-1.1.1.dist-info/WHEEL
elephant/change_point_detection.py
elephant/datasets.py
elephant/current_source_density.py
elephant/signal_processing.py
elephant/waveform_features.py
elephant/sta.py
elephant/VERSION
elephant/spike_train_synchrony.py
elephant/spike_train_surrogates.py
elephant/spike_train_generation.py
elephant/utils.py
elephant/cell_assembly_detection.py
elephant/spike_train_correlation.py
elephant/phase_analysis.py
elephant/unitary_event_analysis.py
elephant/spade.py
elephant/conversion.py
elephant/kernels.py
elephant/statistics.py
elephant/spike_train_dissimilarity.py
elephant/functional_connectivity.py
elephant/cubic.py
elephant/__init__.py
elephant/spectral.py
elephant/trials.py
elephant/neo_tools.py
elephant/functional_connectivity_src/total_spiking_probability_edges.py
elephant/gpfa/gpfa_util.py
elephant/gpfa/gpfa.py
elephant/gpfa/__init__.py
elephant/gpfa/gpfa_core.py
elephant/spade_src/fast_fca.py
elephant/spade_src/LICENSE
elephant/spade_src/__init__.py
elephant/spade_src/fim.cpython-39-x86_64-linux-gnu.so
elephant/spade_src/src/fim.cpp
elephant/spade_src/include/Pattern.h
elephant/spade_src/include/FPTree.h
elephant/spade_src/include/SigTerm.h
elephant/spade_src/include/FrequencyRef.h
elephant/spade_src/include/FPNode.h
elephant/spade_src/include/Types.h
elephant/spade_src/include/Utils.h
elephant/spade_src/include/Defines.h
elephant/spade_src/include/ClosedDetect.h
elephant/spade_src/include/Logger.h
elephant/spade_src/include/Timer.h
elephant/spade_src/include/ClosedTree.h
elephant/spade_src/include/HeapAlloc.h
elephant/spade_src/include/FPGrowth.h
elephant/spade_src/include/Memory.h
elephant/asset/pmat_neighbors.cl
elephant/asset/joint_pmat_old.cu
elephant/asset/asset.py
elephant/asset/joint_pmat.cl
elephant/asset/pmat_neighbors.cu
elephant/asset/joint_pmat.cu
elephant/asset/__init__.py
elephant/test/test_parallel.py
elephant/test/test_sta.py
elephant/test/test_conversion.py
elephant/test/test_cubic.py
