Metadata-Version: 2.1
Name: elephant
Version: 1.1.1
Summary: Elephant is a package for analysis of electrophysiology data in Python
Home-page: http://python-elephant.org
Author: Elephant authors and contributors
Author-email: contact@python-elephant.org
License: BSD
Project-URL: Bug Tracker, https://github.com/NeuralEnsemble/elephant/issues
Project-URL: Documentation, https://elephant.readthedocs.io/en/latest/
Project-URL: Source Code, https://github.com/NeuralEnsemble/elephant
Classifier: Development Status :: 5 - Production/Stable
Classifier: Intended Audience :: Science/Research
Classifier: License :: OSI Approved :: BSD License
Classifier: Natural Language :: English
Classifier: Operating System :: OS Independent
Classifier: Programming Language :: Python :: 3
Classifier: Programming Language :: Python :: 3.8
Classifier: Programming Language :: Python :: 3.9
Classifier: Programming Language :: Python :: 3.10
Classifier: Programming Language :: Python :: 3.11
Classifier: Programming Language :: Python :: 3 :: Only
Classifier: Topic :: Scientific/Engineering
Requires-Python: >=3.8
License-File: LICENSE.txt
Requires-Dist: neo>=0.10.0
Requires-Dist: numpy<2,>=1.19.5
Requires-Dist: quantities>=0.14.1
Requires-Dist: scipy>=1.10.0
Requires-Dist: six>=1.10.0
Requires-Dist: tqdm
Provides-Extra: extras
Requires-Dist: scikit-learn>=0.23.2; extra == "extras"
Requires-Dist: statsmodels>=0.12.1; extra == "extras"
Requires-Dist: jinja2>=2.11.2; extra == "extras"
Provides-Extra: docs
Requires-Dist: numpydoc>=1.1.0; extra == "docs"
Requires-Dist: jupyter>=1.0.0; extra == "docs"
Requires-Dist: sphinx>=3.3.0; extra == "docs"
Requires-Dist: nbsphinx>=0.8.0; extra == "docs"
Requires-Dist: sphinxcontrib-bibtex>1.0.0; extra == "docs"
Requires-Dist: sphinx-tabs>=1.3.0; extra == "docs"
Requires-Dist: matplotlib<3.9.0,>=3.3.2; extra == "docs"
Provides-Extra: tests
Requires-Dist: pytest; extra == "tests"
Requires-Dist: nixio>=1.5.0; extra == "tests"
Provides-Extra: tutorials
Requires-Dist: matplotlib<3.9.0,>=3.3.2; extra == "tutorials"
Requires-Dist: h5py>=3.1.0; extra == "tutorials"
Requires-Dist: nixio>=1.5.0; extra == "tutorials"
Provides-Extra: cuda
Requires-Dist: pycuda>=2020.1; extra == "cuda"
Provides-Extra: opencl
Requires-Dist: pyopencl>=2020.2.2; extra == "opencl"
